simpleplan/__init__.py
simpleplan/cli.py
simpleplan/mcp_server.py
simpleplan/models.py
simpleplan/project_plan_io.py
simpleplan-1.0.3.dist-info/LICENSE
simpleplan-1.0.3.dist-info/METADATA
simpleplan-1.0.3.dist-info/WHEEL
simpleplan-1.0.3.dist-info/entry_points.txt
simpleplan-1.0.3.dist-info/RECORD
