Metadata-Version: 2.3
Name: SimplePlan
Version: 1.0.3
Summary: AI-native project management with MCP integration for universal AI access
License: MIT
Keywords: project-management,ai,mcp,planning,workflow
Author: Sunset Code Collaborative, LLC
Author-email: bjorn@sunsetcodecollaborative.com
Requires-Python: >=3.10,<3.14
Classifier: Development Status :: 5 - Production/Stable
Classifier: Intended Audience :: Developers
Classifier: License :: OSI Approved :: MIT License
Classifier: Programming Language :: Python :: 3
Classifier: Programming Language :: Python :: 3.10
Classifier: Programming Language :: Python :: 3.11
Classifier: Programming Language :: Python :: 3.12
Classifier: Programming Language :: Python :: 3.13
Classifier: Topic :: Office/Business :: Scheduling
Classifier: Topic :: Software Development :: Libraries :: Python Modules
Requires-Dist: click (>=8.1.0,<9.0.0)
Requires-Dist: fastmcp (>=2.10.2,<3.0.0)
Requires-Dist: jinja2 (>=3.1.0,<4.0.0)
Requires-Dist: jsonschema (>=4.20.0,<5.0.0)
Requires-Dist: pydantic (>=2.5.0,<3.0.0)
Requires-Dist: rich (>=13.7.0,<14.0.0)
Project-URL: Documentation, https://github.com/Sunset-Code-Collaborative/SimplePlan/blob/main/README.md
Project-URL: Homepage, https://github.com/Sunset-Code-Collaborative/SimplePlan
Project-URL: Repository, https://github.com/Sunset-Code-Collaborative/SimplePlan
